[
  {
    "id": "208379",
    "name": "Christian Walton",
    "position": "Goalkeeper",
    "number": "28",
    "age": "30",
    "nationality": [
      "England"
    ],
    "market_value": "€1.20m"
  },
  {
    "id": "245625",
    "name": "Alex Palmer",
    "position": "Goalkeeper",
    "number": "1",
    "age": "29",
    "nationality": [
      "England"
    ],
    "market_value": "€1.00m"
  },
  {
    "id": "401320",
    "name": "Dara O'Shea",
    "position": "Centre-Back",
    "number": "26",
    "age": "27",
    "nationality": [
      "Ireland"
    ],
    "market_value": "€15.00m"
  },
  {
    "id": "693095",
    "name": "Jacob Greaves",
    "position": "Centre-Back",
    "number": "24",
    "age": "25",
    "nationality": [
      "England"
    ],
    "market_value": "€14.00m"
  },
  {
    "id": "596446",
    "name": "Leif Davis",
    "position": "Left-Back",
    "number": "3",
    "age": "26",
    "nationality": [
      "England"
    ],
    "market_value": "€20.00m"
  },
  {
    "id": "146509",
    "name": "Conor Townsend",
    "position": "Left-Back",
    "number": "22",
    "age": "33",
    "nationality": [
      "England"
    ],
    "market_value": "€500k"
  },
  {
    "id": "468002",
    "name": "Ben Johnson",
    "position": "Right-Back",
    "number": "18",
    "age": "26",
    "nationality": [
      "England"
    ],
    "market_value": "€7.00m"
  },
  {
    "id": "458178",
    "name": "Jack Taylor",
    "position": "Central Midfield",
    "number": "14",
    "age": "27",
    "nationality": [
      "Ireland",
      "England"
    ],
    "market_value": "€3.00m"
  },
  {
    "id": "255731",
    "name": "Wes Burns",
    "position": "Right Midfield",
    "number": "7",
    "age": "31",
    "nationality": [
      "Wales"
    ],
    "market_value": "€1.80m"
  },
  {
    "id": "665390",
    "name": "Jaden Philogene",
    "position": "Left Winger",
    "number": "11",
    "age": "24",
    "nationality": [
      "England",
      "Dominica"
    ],
    "market_value": "€18.00m"
  },
  {
    "id": "559794",
    "name": "Jack Clarke",
    "position": "Left Winger",
    "number": "47",
    "age": "25",
    "nationality": [
      "England"
    ],
    "market_value": "€18.00m"
  },
  {
    "id": "420808",
    "name": "George Hirst",
    "position": "Centre-Forward",
    "number": "9",
    "age": "27",
    "nationality": [
      "Scotland",
      "England"
    ],
    "market_value": "€8.00m"
  }
]