[
  {
    "id": "403151",
    "name": "Robert Sánchez",
    "position": "Goalkeeper",
    "number": "1",
    "age": "28",
    "nationality": [
      "Spain",
      "England"
    ],
    "market_value": "€22.00m"
  },
  {
    "id": "585323",
    "name": "Filip Jørgensen",
    "position": "Goalkeeper",
    "number": "12",
    "age": "24",
    "nationality": [
      "Denmark",
      "Sweden"
    ],
    "market_value": "€15.00m"
  },
  {
    "id": "656316",
    "name": "Gabriel Slonina",
    "position": "Goalkeeper",
    "number": "44",
    "age": "22",
    "nationality": [
      "United States",
      "Poland"
    ],
    "market_value": "€3.50m"
  },
  {
    "id": "614258",
    "name": "Levi Colwill",
    "position": "Centre-Back",
    "number": "6",
    "age": "23",
    "nationality": [
      "England"
    ],
    "market_value": "€50.00m"
  },
  {
    "id": "346314",
    "name": "Trevoh Chalobah",
    "position": "Centre-Back",
    "number": "23",
    "age": "26",
    "nationality": [
      "England",
      "Sierra Leone"
    ],
    "market_value": "€40.00m"
  },
  {
    "id": "475411",
    "name": "Wesley Fofana",
    "position": "Centre-Back",
    "number": "29",
    "age": "25",
    "nationality": [
      "France",
      "Cote d'Ivoire"
    ],
    "market_value": "€28.00m"
  },
  {
    "id": "258878",
    "name": "Tosin Adarabioyo",
    "position": "Centre-Back",
    "number": "4",
    "age": "28",
    "nationality": [
      "England",
      "Nigeria"
    ],
    "market_value": "€18.00m"
  },
  {
    "id": "463603",
    "name": "Benoît Badiashile",
    "position": "Centre-Back",
    "number": "5",
    "age": "25",
    "nationality": [
      "France",
      "DR Congo"
    ],
    "market_value": "€18.00m"
  },
  {
    "id": "284857",
    "name": "Marc Cucurella",
    "position": "Left-Back",
    "number": "3",
    "age": "27",
    "nationality": [
      "Spain"
    ],
    "market_value": "€50.00m"
  },
  {
    "id": "472423",
    "name": "Reece James",
    "position": "Right-Back",
    "number": "24",
    "age": "26",
    "nationality": [
      "England"
    ],
    "market_value": "€60.00m"
  },
  {
    "id": "620322",
    "name": "Malo Gusto",
    "position": "Right-Back",
    "number": "27",
    "age": "23",
    "nationality": [
      "France",
      "Martinique"
    ],
    "market_value": "€35.00m"
  },
  {
    "id": "1004708",
    "name": "Josh Acheampong",
    "position": "Right-Back",
    "number": "34",
    "age": "20",
    "nationality": [
      "England",
      "Ghana"
    ],
    "market_value": "€25.00m"
  },
  {
    "id": "687626",
    "name": "Moisés Caicedo",
    "position": "Defensive Midfield",
    "number": "25",
    "age": "24",
    "nationality": [
      "Ecuador"
    ],
    "market_value": "€110.00m"
  },
  {
    "id": "628451",
    "name": "Roméo Lavia",
    "position": "Defensive Midfield",
    "number": "45",
    "age": "22",
    "nationality": [
      "Belgium",
      "Ghana"
    ],
    "market_value": "€25.00m"
  },
  {
    "id": "648195",
    "name": "Enzo Fernández",
    "position": "Central Midfield",
    "number": "8",
    "age": "25",
    "nationality": [
      "Argentina"
    ],
    "market_value": "€90.00m"
  },
  {
    "id": "743600",
    "name": "Andrey Santos",
    "position": "Central Midfield",
    "number": "17",
    "age": "22",
    "nationality": [
      "Brazil"
    ],
    "market_value": "€45.00m"
  },
  {
    "id": "568177",
    "name": "Cole Palmer",
    "position": "Attacking Midfield",
    "number": "10",
    "age": "24",
    "nationality": [
      "England",
      "St. Kitts & Nevis"
    ],
    "market_value": "€110.00m"
  },
  {
    "id": "537860",
    "name": "Mykhaylo Mudryk",
    "position": "Left Winger",
    "number": "-",
    "age": "25",
    "nationality": [
      "Ukraine"
    ],
    "market_value": "-"
  },
  {
    "id": "487465",
    "name": "Pedro Neto",
    "position": "Right Winger",
    "number": "7",
    "age": "26",
    "nationality": [
      "Portugal"
    ],
    "market_value": "€60.00m"
  }
]